dojosw/__init__.py
dojosw/music.py
dojosw/musik.py
dojosw/roboter.py
dojosw-0.5.0.dist-info/licenses/LICENSE
dojosw-0.5.0.dist-info/METADATA
dojosw-0.5.0.dist-info/WHEEL
dojosw-0.5.0.dist-info/top_level.txt
dojosw-0.5.0.dist-info/RECORD
