Metadata-Version: 2.4
Name: dojosw
Version: 0.5.0
Summary: Python Bibliothek für das CoderDojo Schöneweide.
Author-email: Bruno Schilling <bruno.schilling@protonmail.ch>
License-Expression: MIT
Requires-Python: >=3.11
License-File: LICENSE
Requires-Dist: numpy>=2.0
Provides-Extra: jupyter
Requires-Dist: ipython>=9.4; extra == "jupyter"
Requires-Dist: jupyturtle>=2024.4; extra == "jupyter"
Provides-Extra: server
Requires-Dist: jupyterlab>=4.4; extra == "server"
Requires-Dist: jupyterlab-language-pack-de-DE; extra == "server"
Dynamic: license-file
